Encrypt_Lab/AWidget.py
Encrypt_Lab/Input.py
Encrypt_Lab/Sim.py
Encrypt_Lab/__init__.py
Encrypt_Lab/abc.py
Encrypt_Lab/temp.py
Encrypt_Lab/__pycache__/AWidget.cpython-38.pyc
Encrypt_Lab/__pycache__/Input.cpython-38.pyc
Encrypt_Lab/__pycache__/Sim.cpython-38.pyc
Encrypt_Lab-0.1.6.dist-info/METADATA
Encrypt_Lab-0.1.6.dist-info/WHEEL
Encrypt_Lab-0.1.6.dist-info/top_level.txt
Encrypt_Lab-0.1.6.dist-info/RECORD
