Metadata-Version: 2.1
Name: Encrypt-Lab
Version: 0.1.6
Summary: Encrypt
Home-page: UNKNOWN
Author: Aviv Gili
Author-email: aviv.orly@netvision.net.il
License: UNKNOWN
Keywords: python
Platform: UNKNOWN
Classifier: Development Status :: 1 - Planning
Classifier: Intended Audience :: Developers
Classifier: Programming Language :: Python :: 3
Requires-Dist: numpy
Requires-Dist: PyQt5
